{
  "data": {
    "user": {
      "sponsorshipsAsMaintainer": {
        "edges": [
          {
            "node": {
              "createdAt": "2019-11-05T03:04:00Z",
              "sponsorEntity": {
                "avatarUrl": "https://avatars.githubusercontent.com/u/21592?u=82e4b54376a216ae3a75f5e0ea2348f35070129d&v=4",
                "login": "inxilpro",
                "name": "Chris Morrell"
              }
            },
            "cursor": "MQ"
          },
          {
            "node": {
              "createdAt": "2019-11-06T19:35:41Z",
              "sponsorEntity": {
                "avatarUrl": "https://avatars.githubusercontent.com/u/6280211?v=4",
                "login": "fourstacks",
                "name": "John Wyles"
              }
            },
            "cursor": "Mg"
          },
          {
            "node": {
              "createdAt": "2019-11-07T19:43:14Z",
              "sponsorEntity": {
                "avatarUrl": "https://avatars.githubusercontent.com/u/588012?u=ae561d4f7f8c07127df4aef9c357e6ceb169edf2&v=4",
                "login": "robindrost",
                "name": "robindrost"
              }
            },
            "cursor": "Mw"
          },
          {
            "node": {
              "createdAt": "2019-11-11T23:23:19Z",
              "sponsorEntity": {
                "avatarUrl": "https://avatars.githubusercontent.com/u/558441?u=93d82087d27e54d0a464a1d290471ad3a74135ac&v=4",
                "login": "michaeldyrynda",
                "name": "Michael Dyrynda"
              }
            },
            "cursor": "NA"
          },
          {
            "node": {
              "createdAt": "2019-11-18T09:16:42Z",
              "sponsorEntity": {
                "avatarUrl": "https://avatars.githubusercontent.com/u/3557?u=323dbfb2c8a7e2bd527d2c4e231dcfab518033c1&v=4",
                "login": "ledermann",
                "name": "Georg Ledermann"
              }
            },
            "cursor": "NQ"
          },
          {
            "node": {
              "createdAt": "2019-11-27T07:46:45Z",
              "sponsorEntity": {
                "avatarUrl": "https://avatars.githubusercontent.com/u/12988164?u=b5f3f2f4ed00761bc38a18f69c9b3f548835a3ec&v=4",
                "login": "Juhlinus",
                "name": "Linus Juhlin"
              }
            },
            "cursor": "Ng"
          },
          {
            "node": {
              "createdAt": "2019-11-27T16:44:06Z",
              "sponsorEntity": {
                "avatarUrl": "https://avatars.githubusercontent.com/u/12276548?u=2b01bf5edc561f8c38dfb2cfa6f65c0888637e54&v=4",
                "login": "PollieDev",
                "name": "Pollie"
              }
            },
            "cursor": "Nw"
          },
          {
            "node": {
              "createdAt": "2019-11-27T17:00:56Z",
              "sponsorEntity": {
                "avatarUrl": "https://avatars.githubusercontent.com/u/16297677?u=854a74df0f9cd10ea14cda05f52b98b6a6a506c7&v=4",
                "login": "jamesburrow23",
                "name": "James Burrow"
              }
            },
            "cursor": "OA"
          },
          {
            "node": {
              "createdAt": "2019-11-27T18:01:17Z",
              "sponsorEntity": {
                "avatarUrl": "https://avatars.githubusercontent.com/u/6016996?u=aa078a91dd2970d048793f7c4532cd5b80589623&v=4",
                "login": "aldo555",
                "name": "Aldo Dumitrescu"
              }
            },
            "cursor": "OQ"
          },
          {
            "node": {
              "createdAt": "2019-11-28T07:59:53Z",
              "sponsorEntity": {
                "avatarUrl": "https://avatars.githubusercontent.com/u/3110750?u=491e77e20cb9c91d83bcac26049669e1b4a9572b&v=4",
                "login": "Cannonb4ll",
                "name": "Dennis Smink"
              }
            },
            "cursor": "MTA"
          },
          {
            "node": {
              "createdAt": "2019-11-28T21:44:20Z",
              "sponsorEntity": {
                "avatarUrl": "https://avatars.githubusercontent.com/u/18542852?u=65241a85b9694d2f23f19e4eb486872cb2e74465&v=4",
                "login": "devcircus",
                "name": "Clayton Stone"
              }
            },
            "cursor": "MTE"
          },
          {
            "node": {
              "createdAt": "2019-11-29T11:10:34Z",
              "sponsorEntity": {
                "avatarUrl": "https://avatars.githubusercontent.com/u/10206461?u=f58afa6af8a4a8364052d703979e3380b12ba010&v=4",
                "login": "JonasPardon",
                "name": "Jonas Pardon"
              }
            },
            "cursor": "MTI"
          },
          {
            "node": {
              "createdAt": "2019-11-30T04:43:23Z",
              "sponsorEntity": {
                "avatarUrl": "https://avatars.githubusercontent.com/u/44739?u=2b4baacdf781daffd9dcc2a18bb0634a2570da67&v=4",
                "login": "jackmcdade",
                "name": "Jack McDade"
              }
            },
            "cursor": "MTM"
          },
          {
            "node": {
              "createdAt": "2019-11-30T21:47:15Z",
              "sponsorEntity": {
                "avatarUrl": "https://avatars.githubusercontent.com/u/8235520?v=4",
                "login": "nathanhipps",
                "name": "Nathan Hipps"
              }
            },
            "cursor": "MTQ"
          },
          {
            "node": {
              "createdAt": "2019-12-01T15:46:39Z",
              "sponsorEntity": {
                "avatarUrl": "https://avatars.githubusercontent.com/u/54643782?u=4621991b7d1ec49cdb9e0f0de1a84569dc349746&v=4",
                "login": "gregupton",
                "name": "Greg Upton"
              }
            },
            "cursor": "MTU"
          },
          {
            "node": {
              "createdAt": "2019-12-03T16:40:33Z",
              "sponsorEntity": {
                "avatarUrl": "https://avatars.githubusercontent.com/u/146465?v=4",
                "login": "troygilbert",
                "name": "Troy Gilbert"
              }
            },
            "cursor": "MTY"
          },
          {
            "node": {
              "createdAt": "2019-12-10T11:36:55Z",
              "sponsorEntity": {
                "avatarUrl": "https://avatars.githubusercontent.com/u/157844?u=1b13ef4d6fc455509b624f587574e5ab11d6d227&v=4",
                "login": "kitar",
                "name": "Satoshi Kita"
              }
            },
            "cursor": "MTc"
          },
          {
            "node": {
              "createdAt": "2019-12-11T17:57:00Z",
              "sponsorEntity": {
                "avatarUrl": "https://avatars.githubusercontent.com/u/767120?u=78c7626bbe55f37ab5ab1bd76c0fbd81870455cb&v=4",
                "login": "hermanschutte",
                "name": "Herman Schutte"
              }
            },
            "cursor": "MTg"
          },
          {
            "node": {
              "createdAt": "2019-12-13T21:10:41Z",
              "sponsorEntity": {
                "avatarUrl": "https://avatars.githubusercontent.com/u/594614?v=4",
                "login": "driesvints",
                "name": "Dries Vints"
              }
            },
            "cursor": "MTk"
          },
          {
            "node": {
              "createdAt": "2019-12-14T08:52:15Z",
              "sponsorEntity": {
                "avatarUrl": "https://avatars.githubusercontent.com/u/1430546?v=4",
                "login": "petersuhm",
                "name": "Peter Suhm"
              }
            },
            "cursor": "MjA"
          },
          {
            "node": {
              "createdAt": "2019-12-20T20:31:04Z",
              "sponsorEntity": {
                "avatarUrl": "https://avatars.githubusercontent.com/u/463230?u=0c486fbe3a30dadd5c5981a9fbc3a0d269ca0c33&v=4",
                "login": "taylorotwell",
                "name": "Taylor Otwell"
              }
            },
            "cursor": "MjE"
          },
          {
            "node": {
              "createdAt": "2019-12-20T21:59:58Z",
              "sponsorEntity": {
                "avatarUrl": "https://avatars.githubusercontent.com/u/1332315?u=6d3fd628a8f5cd670eb947de27999dbb10fc34b8&v=4",
                "login": "trevorgreenleaf",
                "name": "Trevor Greenleaf"
              }
            },
            "cursor": "MjI"
          },
          {
            "node": {
              "createdAt": "2020-01-02T18:14:32Z",
              "sponsorEntity": {
                "avatarUrl": "https://avatars.githubusercontent.com/u/228899?u=b7e53f46e44130b6314684f5d3fc343d5a2fdeb4&v=4",
                "login": "ninjaparade",
                "name": "Ninja"
              }
            },
            "cursor": "MjM"
          },
          {
            "node": {
              "createdAt": "2020-01-08T18:24:25Z",
              "sponsorEntity": {
                "avatarUrl": "https://avatars.githubusercontent.com/u/3144140?v=4",
                "login": "jasoncharnes",
                "name": "Jason Charnes"
              }
            },
            "cursor": "MjQ"
          },
          {
            "node": {
              "createdAt": "2020-01-27T15:30:51Z",
              "sponsorEntity": {
                "avatarUrl": "https://avatars.githubusercontent.com/u/1065551?u=cae0d44e90d3c4f6c02a994974439d7342e71617&v=4",
                "login": "mlantz",
                "name": "Matt Lantz"
              }
            },
            "cursor": "MjU"
          },
          {
            "node": {
              "createdAt": "2020-01-27T17:43:04Z",
              "sponsorEntity": {
                "avatarUrl": "https://avatars.githubusercontent.com/u/755063?u=11ed786b736431f6dd9b6b1ba4a820274472bb3e&v=4",
                "login": "cullymason",
                "name": "Cully Mason"
              }
            },
            "cursor": "MjY"
          },
          {
            "node": {
              "createdAt": "2020-01-27T18:24:49Z",
              "sponsorEntity": {
                "avatarUrl": "https://avatars.githubusercontent.com/u/1053395?u=736fe05783ca11d46d92e7bd3d027c874be93660&v=4",
                "login": "edgrosvenor",
                "name": "Ed Grosvenor"
              }
            },
            "cursor": "Mjc"
          },
          {
            "node": {
              "createdAt": "2020-02-21T09:00:26Z",
              "sponsorEntity": {
                "avatarUrl": "https://avatars.githubusercontent.com/u/2301050?u=32f9c06c712a63545aefebd56a114b348d119e78&v=4",
                "login": "MikeElghali",
                "name": "Mike-e"
              }
            },
            "cursor": "Mjg"
          },
          {
            "node": {
              "createdAt": "2020-03-04T15:56:39Z",
              "sponsorEntity": {
                "avatarUrl": "https://avatars.githubusercontent.com/u/4263996?u=a5abbaec4403836667b5ca506189541f01a9292c&v=4",
                "login": "JoeriAben",
                "name": "Joeri Aben"
              }
            },
            "cursor": "Mjk"
          },
          {
            "node": {
              "createdAt": "2020-03-11T15:33:40Z",
              "sponsorEntity": {
                "avatarUrl": "https://avatars.githubusercontent.com/u/61965317?u=878264da3a5f92e0e08da0651418be1fdfb91478&v=4",
                "login": "top-offerten",
                "name": "top-offerten.ch"
              }
            },
            "cursor": "MzA"
          },
          {
            "node": {
              "createdAt": "2020-03-11T21:01:25Z",
              "sponsorEntity": {
                "avatarUrl": "https://avatars.githubusercontent.com/u/347400?u=d4827035f604e4b3b937c1bd1ade725e94f383f1&v=4",
                "login": "dbpolito",
                "name": "Daniel Polito"
              }
            },
            "cursor": "MzE"
          },
          {
            "node": {
              "createdAt": "2020-04-13T07:59:52Z",
              "sponsorEntity": {
                "avatarUrl": "https://avatars.githubusercontent.com/u/6092928?u=e93fb57e877bf1c1cba76c37b9950e3c4ad66bf3&v=4",
                "login": "Neophen",
                "name": "Mykolas Mankevicius"
              }
            },
            "cursor": "MzI"
          },
          {
            "node": {
              "createdAt": "2020-05-13T12:41:27Z",
              "sponsorEntity": {
                "avatarUrl": "https://avatars.githubusercontent.com/u/8340930?v=4",
                "login": "Jarrid",
                "name": null
              }
            },
            "cursor": "MzM"
          },
          {
            "node": {
              "createdAt": "2020-05-14T01:01:32Z",
              "sponsorEntity": {
                "avatarUrl": "https://avatars.githubusercontent.com/u/203654?u=c358678b17f5ec8bf223c803cb4ce17ab7a19298&v=4",
                "login": "PiranhaGeorge",
                "name": "George Palmer"
              }
            },
            "cursor": "MzQ"
          },
          {
            "node": {
              "createdAt": "2020-05-26T21:45:19Z",
              "sponsorEntity": {
                "avatarUrl": "https://avatars.githubusercontent.com/u/65899150?u=6b64bd7745b4c8739933dd1d1d3302878ce243a0&v=4",
                "login": "liamjoc",
                "name": "Liam O'Connor"
              }
            },
            "cursor": "MzU"
          },
          {
            "node": {
              "createdAt": "2020-06-29T05:54:25Z",
              "sponsorEntity": {
                "avatarUrl": "https://avatars.githubusercontent.com/u/24716811?u=73a0aee770afcfb60c73be334704ed2d10bcf555&v=4",
                "login": "zarsi",
                "name": "Jarkko Hiukka"
              }
            },
            "cursor": "MzY"
          },
          {
            "node": {
              "createdAt": "2020-06-30T18:01:25Z",
              "sponsorEntity": {
                "avatarUrl": "https://avatars.githubusercontent.com/u/18613261?u=fa5b6961e544163122540ce7f71263254a79d58e&v=4",
                "login": "nckrtl",
                "name": "Nick"
              }
            },
            "cursor": "Mzc"
          },
          {
            "node": {
              "createdAt": "2020-07-03T15:18:27Z",
              "sponsorEntity": {
                "avatarUrl": "https://avatars.githubusercontent.com/u/1091085?u=0df875e8632a7348365734613ac5fefc5afb9c90&v=4",
                "login": "mdpoulter",
                "name": "Matthew Poulter"
              }
            },
            "cursor": "Mzg"
          },
          {
            "node": {
              "createdAt": "2020-07-31T07:39:41Z",
              "sponsorEntity": {
                "avatarUrl": "https://avatars.githubusercontent.com/u/1752195?u=c56f28ef56c68bc35d7cb005a3b22fe311b4954f&v=4",
                "login": "claudiodekker",
                "name": "Claudio Dekker"
              }
            },
            "cursor": "Mzk"
          },
          {
            "node": {
              "createdAt": "2020-08-04T21:02:12Z",
              "sponsorEntity": {
                "avatarUrl": "https://avatars.githubusercontent.com/u/270162?u=53be5121ab7ea5d0e5a2275ef1145300af3bef6b&v=4",
                "login": "mikeburrelljr",
                "name": "Mike Burrell, Jr."
              }
            },
            "cursor": "NDA"
          },
          {
            "node": {
              "createdAt": "2020-08-07T09:04:35Z",
              "sponsorEntity": {
                "avatarUrl": "https://avatars.githubusercontent.com/u/5428120?v=4",
                "login": "MianSaleem",
                "name": "Mian Saleem"
              }
            },
            "cursor": "NDE"
          },
          {
            "node": {
              "createdAt": "2020-09-04T11:08:11Z",
              "sponsorEntity": {
                "avatarUrl": "https://avatars.githubusercontent.com/u/12662462?u=50ef77d66fd236b20f426739c4fd31bc33abd9eb&v=4",
                "login": "igerslike",
                "name": null
              }
            },
            "cursor": "NDI"
          },
          {
            "node": {
              "createdAt": "2020-09-09T12:07:43Z",
              "sponsorEntity": {
                "avatarUrl": "https://avatars.githubusercontent.com/u/1569300?v=4",
                "login": "andreiio",
                "name": "Andrei Ioniță"
              }
            },
            "cursor": "NDM"
          },
          {
            "node": {
              "createdAt": "2020-09-26T15:11:31Z",
              "sponsorEntity": {
                "avatarUrl": "https://avatars.githubusercontent.com/u/5927337?v=4",
                "login": "goaround",
                "name": "Johannes Kinast"
              }
            },
            "cursor": "NDQ"
          },
          {
            "node": {
              "createdAt": "2020-10-06T21:55:20Z",
              "sponsorEntity": {
                "avatarUrl": "https://avatars.githubusercontent.com/u/33033094?u=af2f8c68849665a7827be80ba26c1131efff2642&v=4",
                "login": "stancl",
                "name": "Samuel Štancl"
              }
            },
            "cursor": "NDU"
          },
          {
            "node": {
              "createdAt": "2020-10-10T16:24:00Z",
              "sponsorEntity": {
                "avatarUrl": "https://avatars.githubusercontent.com/u/1329131?u=c6ad65b68d857fd478d86a189a25d54f61fff5bc&v=4",
                "login": "scottzirkel",
                "name": "Scott Zirkel"
              }
            },
            "cursor": "NDY"
          },
          {
            "node": {
              "createdAt": "2020-10-11T10:04:01Z",
              "sponsorEntity": {
                "avatarUrl": "https://avatars.githubusercontent.com/u/6657?u=0e994845ae6559b63b6363294904781ec8282fd0&v=4",
                "login": "horaceho",
                "name": "Horace Ho"
              }
            },
            "cursor": "NDc"
          },
          {
            "node": {
              "createdAt": "2020-10-12T21:43:38Z",
              "sponsorEntity": {
                "avatarUrl": "https://avatars.githubusercontent.com/u/25019620?u=94b69220b4ff962e75c34bd0a2cac5df73e89004&v=4",
                "login": "bdweix",
                "name": "Branick Weix"
              }
            },
            "cursor": "NDg"
          },
          {
            "node": {
              "createdAt": "2020-10-13T18:37:22Z",
              "sponsorEntity": {
                "avatarUrl": "https://avatars.githubusercontent.com/u/13928621?u=d76f09ff5eb4c676c102fdbc448638655abfce6a&v=4",
                "login": "ajnsn",
                "name": "Alexander Jensen"
              }
            },
            "cursor": "NDk"
          },
          {
            "node": {
              "createdAt": "2020-10-15T12:54:38Z",
              "sponsorEntity": {
                "avatarUrl": "https://avatars.githubusercontent.com/u/116662?u=2f2cdba858983a58d07b75abfede7914b77bfd16&v=4",
                "login": "ericlbarnes",
                "name": "Eric Barnes"
              }
            },
            "cursor": "NTA"
          },
          {
            "node": {
              "createdAt": "2020-10-21T04:23:08Z",
              "sponsorEntity": {
                "avatarUrl": "https://avatars.githubusercontent.com/u/5139098?u=047aabe9393a1ca0ce1b46828aeff40e724eb08a&v=4",
                "login": "ksassnowski",
                "name": "Kai Sassnowski"
              }
            },
            "cursor": "NTE"
          },
          {
            "node": {
              "createdAt": "2020-11-17T05:50:51Z",
              "sponsorEntity": {
                "avatarUrl": "https://avatars.githubusercontent.com/u/11573528?u=f70558ac43b6ff0a9462b2ea083d34ed3acaf463&v=4",
                "login": "devingray",
                "name": "Devin Gray"
              }
            },
            "cursor": "NTI"
          },
          {
            "node": {
              "createdAt": "2020-11-24T21:28:36Z",
              "sponsorEntity": {
                "avatarUrl": "https://avatars.githubusercontent.com/u/12473463?u=3244121fa8a42a358803d92b59abebf8246e9d9e&v=4",
                "login": "timmurphydev",
                "name": "Tim Murphy"
              }
            },
            "cursor": "NTM"
          },
          {
            "node": {
              "createdAt": "2020-11-26T06:38:42Z",
              "sponsorEntity": {
                "avatarUrl": "https://avatars.githubusercontent.com/u/46476605?v=4",
                "login": "leeloop7",
                "name": null
              }
            },
            "cursor": "NTQ"
          },
          {
            "node": {
              "createdAt": "2020-12-28T14:43:52Z",
              "sponsorEntity": {
                "avatarUrl": "https://avatars.githubusercontent.com/u/26357771?v=4",
                "login": "akaunting",
                "name": "Akaunting"
              }
            },
            "cursor": "NTU"
          },
          {
            "node": {
              "createdAt": "2020-12-28T23:14:09Z",
              "sponsorEntity": {
                "avatarUrl": "https://avatars.githubusercontent.com/u/2871897?u=89fd00ce7e9a0672f3e748ac3200d5f2911739c4&v=4",
                "login": "RobertBoes",
                "name": "Robert Boes"
              }
            },
            "cursor": "NTY"
          },
          {
            "node": {
              "createdAt": "2021-01-02T16:53:20Z",
              "sponsorEntity": {
                "avatarUrl": "https://avatars.githubusercontent.com/u/18236969?u=ed66080e9c15e089a2d446da8698ea6ad948cd3a&v=4",
                "login": "taylormaguire",
                "name": "Taylor Maguire"
              }
            },
            "cursor": "NTc"
          },
          {
            "node": {
              "createdAt": "2021-02-02T18:09:00Z",
              "sponsorEntity": {
                "avatarUrl": "https://avatars.githubusercontent.com/u/20573863?u=dfdc95baeb12809c21a60de747163055d9e08132&v=4",
                "login": "HazJ",
                "name": "Haz"
              }
            },
            "cursor": "NTg"
          },
          {
            "node": {
              "createdAt": "2021-02-16T10:46:05Z",
              "sponsorEntity": {
                "avatarUrl": "https://avatars.githubusercontent.com/u/5393965?u=7a6d373d753b0041596fdfcd35c57d95cc5b48bb&v=4",
                "login": "GuidoHendriks",
                "name": "Guido Hendriks"
              }
            },
            "cursor": "NTk"
          },
          {
            "node": {
              "createdAt": "2021-02-19T22:29:09Z",
              "sponsorEntity": {
                "avatarUrl": "https://avatars.githubusercontent.com/u/3661610?v=4",
                "login": "lucasromanojf",
                "name": "Lucas Romano"
              }
            },
            "cursor": "NjA"
          },
          {
            "node": {
              "createdAt": "2021-02-24T01:00:14Z",
              "sponsorEntity": {
                "avatarUrl": "https://avatars.githubusercontent.com/u/436173?v=4",
                "login": "stephenhowells",
                "name": "Stephen Howells"
              }
            },
            "cursor": "NjE"
          },
          {
            "node": {
              "createdAt": "2021-03-10T00:21:31Z",
              "sponsorEntity": {
                "avatarUrl": "https://avatars.githubusercontent.com/u/74748875?v=4",
                "login": "programodo",
                "name": "Programodo"
              }
            },
            "cursor": "NjI"
          },
          {
            "node": {
              "createdAt": "2021-03-15T16:36:04Z",
              "sponsorEntity": {
                "avatarUrl": "https://avatars.githubusercontent.com/u/1929750?u=2580a0e6a510809d008a8bd6eca0afe11d4c9c68&v=4",
                "login": "xyNNN",
                "name": "Philipp Bräutigam"
              }
            },
            "cursor": "NjM"
          },
          {
            "node": {
              "createdAt": "2021-03-19T10:04:43Z",
              "sponsorEntity": {
                "avatarUrl": "https://avatars.githubusercontent.com/u/151001?u=b812180d156e47df1a233a8b1b7812d99319541e&v=4",
                "login": "vedovelli",
                "name": "Fábio Vedovelli"
              }
            },
            "cursor": "NjQ"
          },
          {
            "node": {
              "createdAt": "2021-03-24T02:06:33Z",
              "sponsorEntity": {
                "avatarUrl": "https://avatars.githubusercontent.com/u/3442006?u=68bcf32be90927ef1ff7f6a2f9e9e60ae107d94b&v=4",
                "login": "neilgilmour",
                "name": "Neil Gilmour"
              }
            },
            "cursor": "NjU"
          },
          {
            "node": {
              "createdAt": "2021-03-25T00:48:47Z",
              "sponsorEntity": {
                "avatarUrl": "https://avatars.githubusercontent.com/u/58970?v=4",
                "login": "davidhemphill",
                "name": "David Hemphill"
              }
            },
            "cursor": "NjY"
          },
          {
            "node": {
              "createdAt": "2021-03-26T11:00:36Z",
              "sponsorEntity": {
                "avatarUrl": "https://avatars.githubusercontent.com/u/68274157?v=4",
                "login": "craigrileyuk",
                "name": "Craig Riley"
              }
            },
            "cursor": "Njc"
          },
          {
            "node": {
              "createdAt": "2021-03-26T22:33:36Z",
              "sponsorEntity": {
                "avatarUrl": "https://avatars.githubusercontent.com/u/29180903?u=8bac9a3e0caef2934870a4503302ccc7b0f08222&v=4",
                "login": "dillingham",
                "name": "Brian Dillingham"
              }
            },
            "cursor": "Njg"
          },
          {
            "node": {
              "createdAt": "2021-03-28T06:06:13Z",
              "sponsorEntity": {
                "avatarUrl": "https://avatars.githubusercontent.com/u/2814277?u=764a754c16f3d8a3c78bd439a884a64620408637&v=4",
                "login": "Olindn",
                "name": null
              }
            },
            "cursor": "Njk"
          },
          {
            "node": {
              "createdAt": "2021-03-28T20:15:41Z",
              "sponsorEntity": {
                "avatarUrl": "https://avatars.githubusercontent.com/u/42443219?u=94a84885b074e48dc380f3afc4c443297a7c7bfa&v=4",
                "login": "camilbinas",
                "name": "Camil Binas"
              }
            },
            "cursor": "NzA"
          },
          {
            "node": {
              "createdAt": "2021-03-29T19:56:53Z",
              "sponsorEntity": {
                "avatarUrl": "https://avatars.githubusercontent.com/u/649677?u=c1ed65fb8e25237f6ea5e71e8c1a086fe760c5b8&v=4",
                "login": "nhedger",
                "name": "Nicolas Hedger"
              }
            },
            "cursor": "NzE"
          },
          {
            "node": {
              "createdAt": "2021-03-29T20:53:19Z",
              "sponsorEntity": {
                "avatarUrl": "https://avatars.githubusercontent.com/u/3351013?u=5fb88ce570f8b4f5a45be9e857dc7547f1ded171&v=4",
                "login": "bjorkgard",
                "name": "Nathanael Björkgård"
              }
            },
            "cursor": "NzI"
          },
          {
            "node": {
              "createdAt": "2021-03-29T21:15:04Z",
              "sponsorEntity": {
                "avatarUrl": "https://avatars.githubusercontent.com/u/13042804?u=47262cb31e2954001454451f87014ac7d7472dfb&v=4",
                "login": "jerredhurst",
                "name": "Jerred Hurst"
              }
            },
            "cursor": "NzM"
          },
          {
            "node": {
              "createdAt": "2021-03-30T18:32:12Z",
              "sponsorEntity": {
                "avatarUrl": "https://avatars.githubusercontent.com/u/1648007?v=4",
                "login": "bmikulic",
                "name": null
              }
            },
            "cursor": "NzQ"
          },
          {
            "node": {
              "createdAt": "2021-04-01T12:50:49Z",
              "sponsorEntity": {
                "avatarUrl": "https://avatars.githubusercontent.com/u/6431835?u=77aa305168999c254e9d1dbc987a11502131f223&v=4",
                "login": "brianakidd",
                "name": "Brian Kidd"
              }
            },
            "cursor": "NzU"
          },
          {
            "node": {
              "createdAt": "2021-04-01T22:11:32Z",
              "sponsorEntity": {
                "avatarUrl": "https://avatars.githubusercontent.com/u/15585?v=4",
                "login": "mixr",
                "name": "Reiner Dieterich"
              }
            },
            "cursor": "NzY"
          },
          {
            "node": {
              "createdAt": "2021-04-06T14:57:26Z",
              "sponsorEntity": {
                "avatarUrl": "https://avatars.githubusercontent.com/u/46318243?u=bc1635220f1201e3c505808ca1e0442dbd1a3e1e&v=4",
                "login": "njones101",
                "name": null
              }
            },
            "cursor": "Nzc"
          },
          {
            "node": {
              "createdAt": "2021-04-07T08:11:23Z",
              "sponsorEntity": {
                "avatarUrl": "https://avatars.githubusercontent.com/u/585890?v=4",
                "login": "goyote",
                "name": "Goyo"
              }
            },
            "cursor": "Nzg"
          },
          {
            "node": {
              "createdAt": "2021-04-07T12:33:36Z",
              "sponsorEntity": {
                "avatarUrl": "https://avatars.githubusercontent.com/u/39373080?u=8878be58ca148f1a88a6c0d338101dd2914b14d0&v=4",
                "login": "SteadfastCollective",
                "name": "Steadfast Collective"
              }
            },
            "cursor": "Nzk"
          },
          {
            "node": {
              "createdAt": "2021-04-09T04:43:58Z",
              "sponsorEntity": {
                "avatarUrl": "https://avatars.githubusercontent.com/u/9354830?v=4",
                "login": "isaackearl",
                "name": "Isaac Earl"
              }
            },
            "cursor": "ODA"
          },
          {
            "node": {
              "createdAt": "2021-04-11T16:46:43Z",
              "sponsorEntity": {
                "avatarUrl": "https://avatars.githubusercontent.com/u/66511791?u=3440276260c4e0c36b3ee210e1ecda6a4c94fade&v=4",
                "login": "ollivr",
                "name": "Ollivr"
              }
            },
            "cursor": "ODE"
          },
          {
            "node": {
              "createdAt": "2021-04-12T19:45:17Z",
              "sponsorEntity": {
                "avatarUrl": "https://avatars.githubusercontent.com/u/82412352?v=4",
                "login": "financeirotalenses",
                "name": null
              }
            },
            "cursor": "ODI"
          },
          {
            "node": {
              "createdAt": "2021-04-14T17:39:48Z",
              "sponsorEntity": {
                "avatarUrl": "https://avatars.githubusercontent.com/u/9700987?v=4",
                "login": "mikestechshop",
                "name": "Mike's Tech Shop"
              }
            },
            "cursor": "ODM"
          },
          {
            "node": {
              "createdAt": "2021-04-14T19:56:34Z",
              "sponsorEntity": {
                "avatarUrl": "https://avatars.githubusercontent.com/u/45166618?u=b28c8d3abf11b5b83a73f6504679f1a7cfe24e8f&v=4",
                "login": "maxacarvalho",
                "name": "Max Carvalho"
              }
            },
            "cursor": "ODQ"
          },
          {
            "node": {
              "createdAt": "2021-04-15T05:04:50Z",
              "sponsorEntity": {
                "avatarUrl": "https://avatars.githubusercontent.com/u/930079?v=4",
                "login": "anthonylebrun",
                "name": "Pierre Lebrun"
              }
            },
            "cursor": "ODU"
          },
          {
            "node": {
              "createdAt": "2021-04-15T09:23:06Z",
              "sponsorEntity": {
                "avatarUrl": "https://avatars.githubusercontent.com/u/3414478?v=4",
                "login": "OMG-DE",
                "name": null
              }
            },
            "cursor": "ODY"
          },
          {
            "node": {
              "createdAt": "2021-04-16T00:38:57Z",
              "sponsorEntity": {
                "avatarUrl": "https://avatars.githubusercontent.com/u/778078?v=4",
                "login": "hwmaier",
                "name": "Henrik Maier"
              }
            },
            "cursor": "ODc"
          },
          {
            "node": {
              "createdAt": "2021-04-16T11:34:41Z",
              "sponsorEntity": {
                "avatarUrl": "https://avatars.githubusercontent.com/u/944061?u=95961fe2b75fc4b8ec8e2314ee505152118a7999&v=4",
                "login": "mattgaunt",
                "name": "Matthew Gaunt"
              }
            },
            "cursor": "ODg"
          },
          {
            "node": {
              "createdAt": "2021-04-20T11:05:54Z",
              "sponsorEntity": {
                "avatarUrl": "https://avatars.githubusercontent.com/u/16915053?u=ad9185849c0f26b00893ea23d9ccbb743c035fc8&v=4",
                "login": "dacoto97",
                "name": "David Cortés"
              }
            },
            "cursor": "ODk"
          },
          {
            "node": {
              "createdAt": "2021-04-20T16:37:25Z",
              "sponsorEntity": {
                "avatarUrl": "https://avatars.githubusercontent.com/u/68554470?u=edbcb2e7df14372dc6514d946ad544464040ed73&v=4",
                "login": "ahowe-scoutapm",
                "name": null
              }
            },
            "cursor": "OTA"
          },
          {
            "node": {
              "createdAt": "2021-04-21T00:26:12Z",
              "sponsorEntity": {
                "avatarUrl": "https://avatars.githubusercontent.com/u/304159?u=79df8e802d2fa59cc8c8df897bb3d23988ffddf5&v=4",
                "login": "swilla",
                "name": "Steve Williamson"
              }
            },
            "cursor": "OTE"
          },
          {
            "node": {
              "createdAt": "2021-04-21T01:12:49Z",
              "sponsorEntity": {
                "avatarUrl": "https://avatars.githubusercontent.com/u/15806912?v=4",
                "login": "worksitesafety",
                "name": "Worksite Safety"
              }
            },
            "cursor": "OTI"
          },
          {
            "node": {
              "createdAt": "2021-04-21T08:09:42Z",
              "sponsorEntity": {
                "avatarUrl": "https://avatars.githubusercontent.com/u/48587703?v=4",
                "login": "steadfast-collective",
                "name": "Steadfast Collective"
              }
            },
            "cursor": "OTM"
          },
          {
            "node": {
              "createdAt": "2021-04-21T10:04:40Z",
              "sponsorEntity": {
                "avatarUrl": "https://avatars.githubusercontent.com/u/6154068?u=7549492132e094e79c80adc2ea174b37312d8003&v=4",
                "login": "peterbrinck",
                "name": "Peter Brinck"
              }
            },
            "cursor": "OTQ"
          },
          {
            "node": {
              "createdAt": "2021-04-21T14:55:41Z",
              "sponsorEntity": {
                "avatarUrl": "https://avatars.githubusercontent.com/u/35864222?u=311ab3fea38ecdc2b7cf4d546151fbe1e8ce17b5&v=4",
                "login": "mvpopuk",
                "name": "Marian Pop"
              }
            },
            "cursor": "OTU"
          },
          {
            "node": {
              "createdAt": "2021-04-23T02:15:56Z",
              "sponsorEntity": {
                "avatarUrl": "https://avatars.githubusercontent.com/u/1181448?u=79f40b51a3f63c771a8b070a0b59fbd9bc83d239&v=4",
                "login": "trea",
                "name": "Trea Hauet"
              }
            },
            "cursor": "OTY"
          },
          {
            "node": {
              "createdAt": "2021-04-23T15:41:07Z",
              "sponsorEntity": {
                "avatarUrl": "https://avatars.githubusercontent.com/u/496255?u=d1ac92023939da60151a029e1426d83c24586619&v=4",
                "login": "hastebrot",
                "name": "Benjamin Gudehus"
              }
            },
            "cursor": "OTc"
          },
          {
            "node": {
              "createdAt": "2021-04-23T16:33:31Z",
              "sponsorEntity": {
                "avatarUrl": "https://avatars.githubusercontent.com/u/61255513?v=4",
                "login": "AryeoHQ",
                "name": "Aryeo"
              }
            },
            "cursor": "OTg"
          },
          {
            "node": {
              "createdAt": "2021-04-24T05:53:11Z",
              "sponsorEntity": {
                "avatarUrl": "https://avatars.githubusercontent.com/u/11378396?v=4",
                "login": "oueki",
                "name": null
              }
            },
            "cursor": "OTk"
          },
          {
            "node": {
              "createdAt": "2021-04-26T00:34:09Z",
              "sponsorEntity": {
                "avatarUrl": "https://avatars.githubusercontent.com/u/420113?u=29e20459ca41547a7fd7c4dfb4414f5ec97e74f6&v=4",
                "login": "christoomey",
                "name": "Chris Toomey"
              }
            },
            "cursor": "MTAw"
          },
          {
            "node": {
              "createdAt": "2021-04-26T11:14:45Z",
              "sponsorEntity": {
                "avatarUrl": "https://avatars.githubusercontent.com/u/36986615?v=4",
                "login": "fabianpnke",
                "name": "Fabian Pankoke"
              }
            },
            "cursor": "MTAx"
          },
          {
            "node": {
              "createdAt": "2021-04-27T03:18:39Z",
              "sponsorEntity": {
                "avatarUrl": "https://avatars.githubusercontent.com/u/28532928?v=4",
                "login": "hoaxduong",
                "name": null
              }
            },
            "cursor": "MTAy"
          }
        ]
      }
    }
  }
}
